diff_pdf_visually/__init__.py
diff_pdf_visually/__main__.py
diff_pdf_visually/constants.py
diff_pdf_visually/diff.py
diff_pdf_visually/external_programs.py
diff_pdf_visually/polyfill.py
diff_pdf_visually-1.8.1.dist-info/METADATA
diff_pdf_visually-1.8.1.dist-info/WHEEL
diff_pdf_visually-1.8.1.dist-info/entry_points.txt
diff_pdf_visually-1.8.1.dist-info/licenses/LICENSE-APACHE
diff_pdf_visually-1.8.1.dist-info/licenses/LICENSE-MIT
diff_pdf_visually-1.8.1.dist-info/RECORD
