Metadata-Version: 2.4
Name: diff-pdf-visually
Version: 1.8.1
Summary: Quickly check whether there is a visible difference between two PDFs, using ImageMagick and pdftocairo.
Project-URL: Homepage, https://github.com/bgeron/diff-pdf-visually
Project-URL: Source, https://github.com/bgeron/diff-pdf-visually
Author-email: Bram Geron <bram@bram.xyz>
Maintainer-email: Bram Geron <bram@bram.xyz>
License-Expression: MIT OR Apache-2.0
License-File: LICENSE-APACHE
License-File: LICENSE-MIT
Classifier: Intended Audience :: Developers
Classifier: License :: OSI Approved :: Apache Software License
Classifier: License :: OSI Approved :: MIT License
Classifier: Natural Language :: English
Classifier: Operating System :: OS Independent
Requires-Python: >=3.8
Provides-Extra: test
Requires-Dist: coverage; extra == 'test'
Requires-Dist: pytest; extra == 'test'
